aidial_interceptors_sdk/chat_completion/__init__.py
aidial_interceptors_sdk/chat_completion/adapter.py
aidial_interceptors_sdk/chat_completion/annotated_value.py
aidial_interceptors_sdk/chat_completion/base.py
aidial_interceptors_sdk/chat_completion/element_path.py
aidial_interceptors_sdk/chat_completion/helpers.py
aidial_interceptors_sdk/chat_completion/index_mapper.py
aidial_interceptors_sdk/chat_completion/request_handler.py
aidial_interceptors_sdk/chat_completion/request_message_handler.py
aidial_interceptors_sdk/chat_completion/response_handler.py
aidial_interceptors_sdk/chat_completion/response_message_handler.py
aidial_interceptors_sdk/dial_client.py
aidial_interceptors_sdk/embeddings/__init__.py
aidial_interceptors_sdk/embeddings/adapter.py
aidial_interceptors_sdk/embeddings/base.py
aidial_interceptors_sdk/error.py
aidial_interceptors_sdk/examples/app.py
aidial_interceptors_sdk/examples/app_factory.py
aidial_interceptors_sdk/examples/chat_completion/__init__.py
aidial_interceptors_sdk/examples/chat_completion/anonymizer/base.py
aidial_interceptors_sdk/examples/chat_completion/anonymizer/impl.py
aidial_interceptors_sdk/examples/chat_completion/anonymizer/replacement.py
aidial_interceptors_sdk/examples/chat_completion/anonymizer/replacements.py
aidial_interceptors_sdk/examples/chat_completion/blacklisted_words.py
aidial_interceptors_sdk/examples/chat_completion/cache.py
aidial_interceptors_sdk/examples/chat_completion/google_dlp_anonymiser/__init__.py
aidial_interceptors_sdk/examples/chat_completion/google_dlp_anonymiser/anonymizer.py
aidial_interceptors_sdk/examples/chat_completion/google_dlp_anonymiser/client.py
aidial_interceptors_sdk/examples/chat_completion/google_dlp_anonymiser/config.py
aidial_interceptors_sdk/examples/chat_completion/google_dlp_anonymiser/impl.py
aidial_interceptors_sdk/examples/chat_completion/image_watermark.py
aidial_interceptors_sdk/examples/chat_completion/langfuse/__init__.py
aidial_interceptors_sdk-0.6.0.dist-info/LICENSE
aidial_interceptors_sdk-0.6.0.dist-info/METADATA
aidial_interceptors_sdk-0.6.0.dist-info/WHEEL
aidial_interceptors_sdk-0.6.0.dist-info/entry_points.txt
aidial_interceptors_sdk-0.6.0.dist-info/RECORD
