Metadata-Version: 2.3
Name: aidial-interceptors-sdk
Version: 0.6.0
Summary: Framework for creating interceptors for AI DIAL
License: Apache-2.0
Keywords: ai
Author: EPAM RAIL
Author-email: SpecialEPM-DIALDevTeam@epam.com
Requires-Python: >=3.11,<3.13
Classifier: Topic :: Software Development :: Libraries :: Python Modules
Provides-Extra: examples
Requires-Dist: aidial-sdk[telemetry] (>=0.21.0)
Requires-Dist: aiostream (==0.6.2) ; extra == "examples"
Requires-Dist: fastapi (>=0.51,<1.0)
Requires-Dist: google-cloud-dlp (==3.30.0) ; extra == "examples"
Requires-Dist: httpx (>=0.25.0,<1.0)
Requires-Dist: langfuse (==2.60.2) ; extra == "examples"
Requires-Dist: numpy (==1.26.4) ; extra == "examples"
Requires-Dist: openai (>=1.32.0,<2.0)
Requires-Dist: pillow (==10.4.0) ; extra == "examples"
Requires-Dist: protobuf (==5.29.5) ; extra == "examples"
Requires-Dist: spacy (==3.7.5) ; extra == "examples"
Project-URL: Documentation, https://epam-rail.com/dial_api
Project-URL: Homepage, https://epam-rail.com
Project-URL: Repository, https://github.com/epam/ai-dial-interceptors-sdk
